cumdistf/__init__.py
cumdistf/cdf.py
cumdistf-0.0.5.dist-info/LICENSE
cumdistf-0.0.5.dist-info/METADATA
cumdistf-0.0.5.dist-info/WHEEL
cumdistf-0.0.5.dist-info/top_level.txt
cumdistf-0.0.5.dist-info/RECORD
