Metadata-Version: 2.1
Name: cumdistf
Version: 0.0.5
Summary: Compute and use cumulative distribution and quantile functions
Home-page: https://github.com/ecpoppenheimer/cumdistf
Author: Eric Poppenheimer
Author-email: ecpoppenheimer@gmail.com
Classifier: Programming Language :: Python :: 3
Classifier: License :: OSI Approved :: MIT License
Classifier: Operating System :: OS Independent
License-File: LICENSE
